MANIFEST.in
PKG-INFO
README.md
ez_setup.py
setup.cfg
setup.py
Pyntheon.egg-info/PKG-INFO
Pyntheon.egg-info/SOURCES.txt
Pyntheon.egg-info/dependency_links.txt
Pyntheon.egg-info/entry_points.txt
Pyntheon.egg-info/not-zip-safe
Pyntheon.egg-info/top_level.txt
examples/Cosmic_data.txt
examples/arabidopsis+thaliana-active_data.txt
examples/human_cancer-data_fucntional-regions.txt
examples/human_cancer_modified_proteins.txt
examples/id_Arabidopsis_thaliana_Resistance_proteins.txt
pyntheon/Amphimedon+queenslandica-PTMs.txt
pyntheon/Anolis+carolinensis.gffPTMs.txt
pyntheon/Aplysia-PTMs.txt
pyntheon/Arbacia+punctulata-PTMs.txt
pyntheon/Ashbya+gossypii.gff-PTMs.txt
pyntheon/Aspergillus+nidulans.gff-PTMs.txt
pyntheon/Bombina+maxima.gff-PTMs.txt
pyntheon/Bombina+orientalis.gff-PTMs.txt
pyntheon/Brachypodium+distachyon.gff-PTMs.txt
pyntheon/Branchiostoma+floridae-PTMs.txt
pyntheon/Caenorhabditis+elegans-functional_data.txt
pyntheon/Canis+lupus.gff-PTMs.txt
pyntheon/Cavia+porcellus.gff-PTMs.txt
pyntheon/Chlamydomonas+reinhardtii.gff-PTMs.txt
pyntheon/Ciona+intestinalis-PTMs.txt
pyntheon/Columba+livia+domestica.gff-PTMs.txt
pyntheon/Coprinus+cinereus.gff-PTMs.txt
pyntheon/Cryptococcus+neoformans.gff-PTMs.txt
pyntheon/Daphnia+magna-PTMs.txt
pyntheon/Dictyostelium+discoideum.gff-PTMs.txt
pyntheon/Emiliania+huxleyi.gff-PTMs.txt
pyntheon/Escherichia+coli-functional_data.txt
pyntheon/Euprymna+scolopes-PTMs.txt
pyntheon/Felis+catus.gff-PTMs.txt
pyntheon/Galleria+mellonella-PTMs.txt
pyntheon/Gallus+gallus.gff-PTMs.txt
pyntheon/Gasterosteus+aculeatus.gff-PTMs.txt
pyntheon/Gryllus+bimaculatus-PTMs.txt
pyntheon/Herpes+simplex+virus-PTMs.txt
pyntheon/Heterocephalus+glaber.gff-PTMs.txt
pyntheon/Hydra-PTMs.txt
pyntheon/Lemna+gibba.gff-PTMs.txt
pyntheon/Loligo+pealei-PTMs.txt
pyntheon/Lotus+japonicus.gff-PTMs.txt
pyntheon/Medicago+truncatula.gff-PTMs.txt
pyntheon/Mesocricetus+auratus.gff-PTMs.txt
pyntheon/Mimulus+guttatus.gff-PTMs.txt
pyntheon/Mus+musculus.gff-PTMs.txt
pyntheon/Mycobacterium+tuberculosis-functional_data.txt
pyntheon/Myotis+lucifugus.gff-PTMs.txt
pyntheon/Nematostella+vectensis-PTMs.txt
pyntheon/Neurospora+crassa-PTMs.txt
pyntheon/Nicotiana+benthamiana.gff-PTMs.txt
