Metadata-Version: 1.1
Name: Pyntheon
Version: 0.1
Summary: An automated tool to map mutations to Post Translational Modifitcaions (PTMs)
Home-page: https://github.com/AhmedArslan/ptmAction
Author: Ahmed Arslan
Author-email: ahmed.arslan@kuleuven.be
License: MIT
Keywords: Bioinformatics,Protein variants,PTMs,Protein functoinal regions,UniMap
Platform: UNKNOWN
Classifier: Intended Audience :: Science/Research
Classifier: Topic :: Education
Classifier: License :: OSI Approved :: MIT License
Classifier: Programming Language :: Python :: 2.7
Classifier: Programming Language :: Python :: 3
Classifier: Programming Language :: Python :: 3.3
Classifier: Programming Language :: Python :: 3.4
Classifier: Programming Language :: Python :: 3.5
